README.md
setup.cfg
setup.py
pkuchive/__init__.py
pkuchive/__main__.py
pkuchive/archive_map.arc
pkuchive.egg-info/PKG-INFO
pkuchive.egg-info/SOURCES.txt
pkuchive.egg-info/dependency_links.txt
pkuchive.egg-info/entry_points.txt
pkuchive.egg-info/requires.txt
pkuchive.egg-info/top_level.txt