Metadata-Version: 1.2
Name: pkuchive
Version: 1.0.3
Summary: A tool for OIer to tag the archive folder provided by PKU openjudge (POJ) archive service.
Home-page: https://github.com/enkerewpo/pkuchive
Author: Kvar_ispw17
Author-email: enkerewpo@gmail.com
License: GPL3
Download-URL: https://github.com/enkerewpo/pkuchive/releases/download/1.0.1/pkuchive_release_1.0.2_20170916.tar.gz
Keywords: acm-icpc,noip,noi,openjudge 
Platform: UNKNOWN
Classifier: Development Status :: 3 - Alpha
Classifier: Operating System :: POSIX :: Linux
Classifier: Programming Language :: Python :: 2.7
Requires-Python: <3
